deepfos/__init__.py
deepfos/_version.py
deepfos/cache.py
deepfos/config.py
deepfos/lazy.py
deepfos/lazy_import.py
deepfos/local.py
deepfos/options.py
deepfos/translation.py
deepfos/algo/__init__.py
deepfos/algo/graph.py
deepfos/algo/segtree.py
deepfos/api/__init__.py
deepfos/api/account.py
deepfos/api/accounting_engines.py
deepfos/api/app.py
deepfos/api/approval_process.py
deepfos/api/base.py
deepfos/api/business_model.py
deepfos/api/consolidation.py
deepfos/api/consolidation_process.py
deepfos/api/datatable.py
deepfos/api/deep_pipeline.py
deepfos/api/deepconnector.py
deepfos/api/deepfos_task.py
deepfos/api/deepmodel.py
deepfos/api/dimension.py
deepfos/api/financial_model.py
deepfos/api/journal_model.py
deepfos/api/journal_template.py
deepfos/api/memory_financial_model.py
deepfos/api/platform.py
deepfos/api/python.py
deepfos/api/reconciliation_engine.py
deepfos/api/reconciliation_report.py
deepfos/api/role_strategy.py
deepfos/api/smartlist.py
deepfos/api/space.py
deepfos/api/system.py
deepfos/api/variable.py
deepfos/api/workflow.py
deepfos/api/V1_1/__init__.py
deepfos/api/V1_1/business_model.py
deepfos/api/V1_1/dimension.py
deepfos/api/V1_1/models/__init__.py
deepfos/api/V1_1/models/business_model.py
deepfos/api/V1_1/models/dimension.py
deepfos/api/V1_2/__init__.py
deepfos/api/V1_2/dimension.py
deepfos/api/V1_2/models/__init__.py
deepfos/api/V1_2/models/dimension.py
deepfos/api/models/__init__.py
deepfos/api/models/account.py
deepfos/api/models/accounting_engines.py
deepfos/api/models/app.py
deepfos/api/models/approval_process.py
deepfos/api/models/base.py
deepfos/api/models/business_model.py
deepfos/api/models/consolidation.py
deepfos/api/models/consolidation_process.py
deepfos/api/models/datatable_mysql.py
deepfos/api/models/deep_pipeline.py
deepfos/api/models/deepconnector.py
deepfos/api/models/deepfos_task.py
deepfos/api/models/deepmodel.py
deepfos/api/models/dimension.py
deepfos/api/models/financial_model.py
deepfos/api/models/journal_model.py
deepfos-1.1.78.dist-info/METADATA
deepfos-1.1.78.dist-info/WHEEL
deepfos-1.1.78.dist-info/top_level.txt
deepfos-1.1.78.dist-info/RECORD
